enough/__init__.py
enough/__main__.py
enough/journaler.py
enough_journal-0.4.0.dist-info/licenses/LICENSE
enough_journal-0.4.0.dist-info/METADATA
enough_journal-0.4.0.dist-info/WHEEL
enough_journal-0.4.0.dist-info/entry_points.txt
enough_journal-0.4.0.dist-info/top_level.txt
enough_journal-0.4.0.dist-info/RECORD
