Metadata-Version: 2.4
Name: enough-journal
Version: 0.4.0
Summary: Nathaniel Branden Sentence Completion Journal
Author-email: DAX <dax@example.com>
License: CC0-1.0
Project-URL: Homepage, https://github.com/sipistab/ENOUGH
Project-URL: Repository, https://github.com/sipistab/ENOUGH
Classifier: Development Status :: 4 - Beta
Classifier: Intended Audience :: End Users/Desktop
Classifier: License :: CC0 1.0 Universal (CC0 1.0) Public Domain Dedication
Classifier: Operating System :: OS Independent
Classifier: Programming Language :: Python :: 3
Classifier: Programming Language :: Python :: 3.8
Classifier: Programming Language :: Python :: 3.9
Classifier: Programming Language :: Python :: 3.10
Classifier: Programming Language :: Python :: 3.11
Classifier: Programming Language :: Python :: 3.12
Classifier: Programming Language :: Python :: 3.13
Requires-Python: >=3.8
License-File: LICENSE
Requires-Dist: PyYAML>=6.0.0
Dynamic: license-file
